Metadata-Version: 1.0
Name: jsonwidget
Version: 0.1.7
Summary: jsonwidget is a general-purpose JSON validation and manipulation, and form-building library for terminal windows and web pages
Home-page: http://robla.net/jsonwidget
Author: Rob Lanphier
Author-email: robla@robla.net
License: BSD
Keywords: json form
Platform: UNKNOWN
Classifier: Development Status :: 3 - Alpha
Classifier: Environment :: Console :: Curses
Classifier: Intended Audience :: Developers
Classifier: License :: OSI Approved :: BSD License
Classifier: Operating System :: POSIX
Classifier: Programming Language :: Python :: 2.4
Classifier: Programming Language :: Python :: 2.5
Classifier: Programming Language :: Python :: 2.6
Classifier: Topic :: Software Development :: Libraries :: Python Modules
Classifier: Topic :: Software Development :: User Interfaces
Classifier: Topic :: Text Editors
